requre/__init__.py
requre/base_testclass.py
requre/cassette.py
requre/constants.py
requre/exceptions.py
requre/guess_object.py
requre/import_system.py
requre/modules_decorate_all_methods.py
requre/objects.py
requre/online_replacing.py
requre/postprocessing.py
requre/pytest_fixtures.py
requre/record_and_replace.py
requre/requre_patch.py
requre/simple_object.py
requre/singleton.py
requre/storage.py
requre/utils.py
requre/helpers/__init__.py
requre/helpers/files.py
requre/helpers/function_output.py
requre/helpers/guess_object.py
requre/helpers/httpx_response.py
requre/helpers/requests_response.py
requre/helpers/simple_object.py
requre/helpers/tempfile.py
requre/helpers/git/__init__.py
requre/helpers/git/fetchinfo.py
requre/helpers/git/helper.py
requre/helpers/git/pushinfo.py
requre/helpers/git/repo.py
requre-0.9.1.dist-info/METADATA
requre-0.9.1.dist-info/WHEEL
requre-0.9.1.dist-info/entry_points.txt
requre-0.9.1.dist-info/licenses/LICENSE
requre-0.9.1.dist-info/RECORD
