Metadata-Version: 2.4
Name: requre
Version: 0.9.1
Summary: Library for testing Python code that allows to store output of various objects and use the stored data for testing.
Project-URL: Homepage, https://github.com/packit/requre
Author-email: Red Hat <packit@redhat.com>
License-Expression: MIT
License-File: LICENSE
Keywords: persistent_storage,session_storage,testing
Classifier: Development Status :: 4 - Beta
Classifier: Environment :: Console
Classifier: Intended Audience :: Developers
Classifier: License :: OSI Approved :: MIT License
Classifier: Operating System :: POSIX :: Linux
Classifier: Programming Language :: Python
Classifier: Programming Language :: Python :: 3.6
Classifier: Programming Language :: Python :: 3.7
Classifier: Topic :: Software Development
Classifier: Topic :: Utilities
Requires-Python: >=3.6
Requires-Dist: click
Requires-Dist: gitpython
Requires-Dist: httpx
Requires-Dist: pytest
Requires-Dist: pyyaml
Requires-Dist: requests
Provides-Extra: testing
Requires-Dist: pytest; extra == 'testing'
